discotool/__init__.py
discotool/__main__.py
discotool/discotool.py
discotool/usbinfos/__init__.py
discotool/usbinfos/pyserial_list_ports_osx.py
discotool/usbinfos/pyserial_list_ports_windows.py
discotool/usbinfos/usbinfos_common.py
discotool/usbinfos/usbinfos_linux.py
discotool/usbinfos/usbinfos_macos.py
discotool/usbinfos/usbinfos_win32.py
discotool_for_microcontrollers-0.1.6.dist-info/LICENSE
discotool_for_microcontrollers-0.1.6.dist-info/METADATA
discotool_for_microcontrollers-0.1.6.dist-info/WHEEL
discotool_for_microcontrollers-0.1.6.dist-info/entry_points.txt
discotool_for_microcontrollers-0.1.6.dist-info/top_level.txt
discotool_for_microcontrollers-0.1.6.dist-info/RECORD
